{"total_count": 4, "incomplete_results": false, "items": [{"id": 105363726, "node_id": "MDEwOlJlcG9zaXRvcnkxMDUzNjM3MjY=", "name": "martin", "full_name": "maplibre/martin", "private": false, "owner": {"login": "maplibre", "id": 75709127, "node_id": "MDEyOk9yZ2FuaXphdGlvbjc1NzA5MTI3", "avatar_url": "https://avatars.githubusercontent.com/u/75709127?v=4", "gravatar_id": "", "url": "https://api.github.com/users/maplibre", "html_url": "https://github.com/maplibre", "followers_url": "https://api.github.com/users/maplibre/followers", "following_url": "https://api.github.com/users/maplibre/following{/other_user}", "gists_url": "https://api.github.com/users/maplibre/gists{/gist_id}", "starred_url": "https://api.github.com/users/maplibre/starred{/owner}{/repo}", "subscriptions_url": "https://api.github.com/users/maplibre/subscriptions", "organizations_url": "https://api.github.com/users/maplibre/orgs", "repos_url": "https://api.github.com/users/maplibre/repos", "events_url": "https://api.github.com/users/maplibre/events{/privacy}", "received_events_url": "https://api.github.com/users/maplibre/received_events", "type": "Organization", "site_admin": false}, "html_url": "https://github.com/maplibre/martin", "description": "Blazing fast and lightweight PostGIS vector tiles server", "fork": false, "url": "https://api.github.com/repos/maplibre/martin", "forks_url": "https://api.github.com/repos/maplibre/martin/forks", "keys_url": "https://api.github.com/repos/maplibre/martin/keys{/key_id}", "collaborators_url": "https://api.github.com/repos/maplibre/martin/collaborators{/collaborator}", "teams_url": "https://api.github.com/repos/maplibre/martin/teams", "hooks_url": "https://api.github.com/repos/maplibre/martin/hooks", "issue_events_url": "https://api.github.com/repos/maplibre/martin/issues/events{/number}", "events_url": "https://api.github.com/repos/maplibre/martin/events", "assignees_url": "https://api.github.com/repos/maplibre/martin/assignees{/user}", "branches_url": "https://api.github.com/repos/maplibre/martin/branches{/branch}", "tags_url": "https://api.github.com/repos/maplibre/martin/tags", "blobs_url": "https://api.github.com/repos/maplibre/martin/git/blobs{/sha}", "git_tags_url": "https://api.github.com/repos/maplibre/martin/git/tags{/sha}", "git_refs_url": "https://api.github.com/repos/maplibre/martin/git/refs{/sha}", "trees_url": "https://api.github.com/repos/maplibre/martin/git/trees{/sha}", "statuses_url": "https://api.github.com/repos/maplibre/martin/statuses/{sha}", "languages_url": "https://api.github.com/repos/maplibre/martin/languages", "stargazers_url": "https://api.github.com/repos/maplibre/martin/stargazers", "contributors_url": "https://api.github.com/repos/maplibre/martin/contributors", "subscribers_url": "https://api.github.com/repos/maplibre/martin/subscribers", "subscription_url": "https://api.github.com/repos/maplibre/martin/subscription", "commits_url": "https://api.github.com/repos/maplibre/martin/commits{/sha}", "git_commits_url": "https://api.github.com/repos/maplibre/martin/git/commits{/sha}", "comments_url": "https://api.github.com/repos/maplibre/martin/comments{/number}", "issue_comment_url": "https://api.github.com/repos/maplibre/martin/issues/comments{/number}", "contents_url": "https://api.github.com/repos/maplibre/martin/contents/{+path}", "compare_url": "https://api.github.com/repos/maplibre/martin/compare/{base}...{head}", "merges_url": "https://api.github.com/repos/maplibre/martin/merges", "archive_url": "https://api.github.com/repos/maplibre/martin/{archive_format}{/ref}", "downloads_url": "https://api.github.com/repos/maplibre/martin/downloads", "issues_url": "https://api.github.com/repos/maplibre/martin/issues{/number}", "pulls_url": "https://api.github.com/repos/maplibre/martin/pulls{/number}", "milestones_url": "https://api.github.com/repos/maplibre/martin/milestones{/number}", "notifications_url": "https://api.github.com/repos/maplibre/martin/notifications{?since,all,participating}", "labels_url": "https://api.github.com/repos/maplibre/martin/labels{/name}", "releases_url": "https://api.github.com/repos/maplibre/martin/releases{/id}", "deployments_url": "https://api.github.com/repos/maplibre/martin/deployments", "created_at": "2017-09-30T10:53:46Z", "updated_at": "2022-06-10T21:25:57Z", "pushed_at": "2022-06-11T07:51:42Z", "git_url": "git://github.com/maplibre/martin.git", "ssh_url": "git@github.com:maplibre/martin.git", "clone_url": "https://github.com/maplibre/martin.git", "svn_url": "https://github.com/maplibre/martin", "homepage": "https://martin.urbica.co", "size": 1411, "stargazers_count": 753, "watchers_count": 753, "language": "Rust", "has_issues": true, "has_projects": false, "has_downloads": true, "has_wiki": false, "has_pages": false, "forks_count": 83, "mirror_url": null, "archived": false, "disabled": false, "open_issues_count": 14, "license": {"key": "mit", "name": "MIT License", "spdx_id": "MIT", "url": "https://api.github.com/licenses/mit", "node_id": "MDc6TGljZW5zZTEz"}, "allow_forking": true, "is_template": false, "topics": ["hacktoberfest", "leaflet", "mapbox", "mapbox-gl", "mapbox-gl-js", "mapbox-vector-tile", "maps", "postgis", "postgresql", "rust", "vector-tiles", "webserver"], "visibility": "public", "forks": 83, "open_issues": 14, "watchers": 753, "default_branch": "main", "permissions": {"admin": false, "maintain": false, "push": false, "triage": false, "pull": true}, "score": 1.0}, {"id": 86180500, "node_id": "MDEwOlJlcG9zaXRvcnk4NjE4MDUwMA==", "name": "cubostratus", "full_name": "rabbitstack/cubostratus", "private": false, "owner": {"login": "rabbitstack", "id": 11174375, "node_id": "MDQ6VXNlcjExMTc0Mzc1", "avatar_url": "https://avatars.githubusercontent.com/u/11174375?v=4", "gravatar_id": "", "url": "https://api.github.com/users/rabbitstack", "html_url": "https://github.com/rabbitstack", "followers_url": "https://api.github.com/users/rabbitstack/followers", "following_url": "https://api.github.com/users/rabbitstack/following{/other_user}", "gists_url": "https://api.github.com/users/rabbitstack/gists{/gist_id}", "starred_url": "https://api.github.com/users/rabbitstack/starred{/owner}{/repo}", "subscriptions_url": "https://api.github.com/users/rabbitstack/subscriptions", "organizations_url": "https://api.github.com/users/rabbitstack/orgs", "repos_url": "https://api.github.com/users/rabbitstack/repos", "events_url": "https://api.github.com/users/rabbitstack/events{/privacy}", "received_events_url": "https://api.github.com/users/rabbitstack/received_events", "type": "User", "site_admin": false}, "html_url": "https://github.com/rabbitstack/cubostratus", "description": "Blazingly fast Linux syscall collector", "fork": false, "url": "https://api.github.com/repos/rabbitstack/cubostratus", "forks_url": "https://api.github.com/repos/rabbitstack/cubostratus/forks", "keys_url": "https://api.github.com/repos/rabbitstack/cubostratus/keys{/key_id}", "collaborators_url": "https://api.github.com/repos/rabbitstack/cubostratus/collaborators{/collaborator}", "teams_url": "https://api.github.com/repos/rabbitstack/cubostratus/teams", "hooks_url": "https://api.github.com/repos/rabbitstack/cubostratus/hooks", "issue_events_url": "https://api.github.com/repos/rabbitstack/cubostratus/issues/events{/number}", "events_url": "https://api.github.com/repos/rabbitstack/cubostratus/events", "assignees_url": "https://api.github.com/repos/rabbitstack/cubostratus/assignees{/user}", "branches_url": "https://api.github.com/repos/rabbitstack/cubostratus/branches{/branch}", "tags_url": "https://api.github.com/repos/rabbitstack/cubostratus/tags", "blobs_url": "https://api.github.com/repos/rabbitstack/cubostratus/git/blobs{/sha}", "git_tags_url": "https://api.github.com/repos/rabbitstack/cubostratus/git/tags{/sha}", "git_refs_url": "https://api.github.com/repos/rabbitstack/cubostratus/git/refs{/sha}", "trees_url": "https://api.github.com/repos/rabbitstack/cubostratus/git/trees{/sha}", "statuses_url": "https://api.github.com/repos/rabbitstack/cubostratus/statuses/{sha}", "languages_url": "https://api.github.com/repos/rabbitstack/cubostratus/languages", "stargazers_url": "https://api.github.com/repos/rabbitstack/cubostratus/stargazers", "contributors_url": "https://api.github.com/repos/rabbitstack/cubostratus/contributors", "subscribers_url": "https://api.github.com/repos/rabbitstack/cubostratus/subscribers", "subscription_url": "https://api.github.com/repos/rabbitstack/cubostratus/subscription", "commits_url": "https://api.github.com/repos/rabbitstack/cubostratus/commits{/sha}", "git_commits_url": "https://api.github.com/repos/rabbitstack/cubostratus/git/commits{/sha}", "comments_url": "https://api.github.com/repos/rabbitstack/cubostratus/comments{/number}", "issue_comment_url": "https://api.github.com/repos/rabbitstack/cubostratus/issues/comments{/number}", "contents_url": "https://api.github.com/repos/rabbitstack/cubostratus/contents/{+path}", "compare_url": "https://api.github.com/repos/rabbitstack/cubostratus/compare/{base}...{head}", "merges_url": "https://api.github.com/repos/rabbitstack/cubostratus/merges", "archive_url": "https://api.github.com/repos/rabbitstack/cubostratus/{archive_format}{/ref}", "downloads_url": "https://api.github.com/repos/rabbitstack/cubostratus/downloads", "issues_url": "https://api.github.com/repos/rabbitstack/cubostratus/issues{/number}", "pulls_url": "https://api.github.com/repos/rabbitstack/cubostratus/pulls{/number}", "milestones_url": "https://api.github.com/repos/rabbitstack/cubostratus/milestones{/number}", "notifications_url": "https://api.github.com/repos/rabbitstack/cubostratus/notifications{?since,all,participating}", "labels_url": "https://api.github.com/repos/rabbitstack/cubostratus/labels{/name}", "releases_url": "https://api.github.com/repos/rabbitstack/cubostratus/releases{/id}", "deployments_url": "https://api.github.com/repos/rabbitstack/cubostratus/deployments", "created_at": "2017-03-25T18:43:07Z", "updated_at": "2022-02-17T03:46:56Z", "pushed_at": "2018-03-10T19:50:12Z", "git_url": "git://github.com/rabbitstack/cubostratus.git", "ssh_url": "git@github.com:rabbitstack/cubostratus.git", "clone_url": "https://github.com/rabbitstack/cubostratus.git", "svn_url": "https://github.com/rabbitstack/cubostratus", "homepage": null, "size": 43, "stargazers_count": 73, "watchers_count": 73, "language": "Rust", "has_issues": true, "has_projects": true, "has_downloads": true, "has_wiki": true, "has_pages": false, "forks_count": 2, "mirror_url": null, "archived": false, "disabled": false, "open_issues_count": 0, "license": {"key": "apache-2.0", "name": "Apache License 2.0", "spdx_id": "Apache-2.0", "url": "https://api.github.com/licenses/apache-2.0", "node_id": "MDc6TGljZW5zZTI="}, "allow_forking": true, "is_template": false, "topics": ["cgroups", "containers", "instrumentation", "linux-kernel", "rust", "syscalls"], "visibility": "public", "forks": 2, "open_issues": 0, "watchers": 73, "default_branch": "master", "permissions": {"admin": false, "maintain": false, "push": false, "triage": false, "pull": true}, "score": 1.0}, {"id": 83187078, "node_id": "MDEwOlJlcG9zaXRvcnk4MzE4NzA3OA==", "name": "munch.rs", "full_name": "utkarshkukreti/munch.rs", "private": false, "owner": {"login": "utkarshkukreti", "id": 217126, "node_id": "MDQ6VXNlcjIxNzEyNg==", "avatar_url": "https://avatars.githubusercontent.com/u/217126?v=4", "gravatar_id": "", "url": "https://api.github.com/users/utkarshkukreti", "html_url": "https://github.com/utkarshkukreti", "followers_url": "https://api.github.com/users/utkarshkukreti/followers", "following_url": "https://api.github.com/users/utkarshkukreti/following{/other_user}", "gists_url": "https://api.github.com/users/utkarshkukreti/gists{/gist_id}", "starred_url": "https://api.github.com/users/utkarshkukreti/starred{/owner}{/repo}", "subscriptions_url": "https://api.github.com/users/utkarshkukreti/subscriptions", "organizations_url": "https://api.github.com/users/utkarshkukreti/orgs", "repos_url": "https://api.github.com/users/utkarshkukreti/repos", "events_url": "https://api.github.com/users/utkarshkukreti/events{/privacy}", "received_events_url": "https://api.github.com/users/utkarshkukreti/received_events", "type": "User", "site_admin": false}, "html_url": "https://github.com/utkarshkukreti/munch.rs", "description": "Blazing fast, zero-copy parser combinator library for Rust with an elegant API for both strings and bytes.", "fork": false, "url": "https://api.github.com/repos/utkarshkukreti/munch.rs", "forks_url": "https://api.github.com/repos/utkarshkukreti/munch.rs/forks", "keys_url": "https://api.github.com/repos/utkarshkukreti/munch.rs/keys{/key_id}", "collaborators_url": "https://api.github.com/repos/utkarshkukreti/munch.rs/collaborators{/collaborator}", "teams_url": "https://api.github.com/repos/utkarshkukreti/munch.rs/teams", "hooks_url": "https://api.github.com/repos/utkarshkukreti/munch.rs/hooks", "issue_events_url": "https://api.github.com/repos/utkarshkukreti/munch.rs/issues/events{/number}", "events_url": "https://api.github.com/repos/utkarshkukreti/munch.rs/events", "assignees_url": "https://api.github.com/repos/utkarshkukreti/munch.rs/assignees{/user}", "branches_url": "https://api.github.com/repos/utkarshkukreti/munch.rs/branches{/branch}", "tags_url": "https://api.github.com/repos/utkarshkukreti/munch.rs/tags", "blobs_url": "https://api.github.com/repos/utkarshkukreti/munch.rs/git/blobs{/sha}", "git_tags_url": "https://api.github.com/repos/utkarshkukreti/munch.rs/git/tags{/sha}", "git_refs_url": "https://api.github.com/repos/utkarshkukreti/munch.rs/git/refs{/sha}", "trees_url": "https://api.github.com/repos/utkarshkukreti/munch.rs/git/trees{/sha}", "statuses_url": "https://api.github.com/repos/utkarshkukreti/munch.rs/statuses/{sha}", "languages_url": "https://api.github.com/repos/utkarshkukreti/munch.rs/languages", "stargazers_url": "https://api.github.com/repos/utkarshkukreti/munch.rs/stargazers", "contributors_url": "https://api.github.com/repos/utkarshkukreti/munch.rs/contributors", "subscribers_url": "https://api.github.com/repos/utkarshkukreti/munch.rs/subscribers", "subscription_url": "https://api.github.com/repos/utkarshkukreti/munch.rs/subscription", "commits_url": "https://api.github.com/repos/utkarshkukreti/munch.rs/commits{/sha}", "git_commits_url": "https://api.github.com/repos/utkarshkukreti/munch.rs/git/commits{/sha}", "comments_url": "https://api.github.com/repos/utkarshkukreti/munch.rs/comments{/number}", "issue_comment_url": "https://api.github.com/repos/utkarshkukreti/munch.rs/issues/comments{/number}", "contents_url": "https://api.github.com/repos/utkarshkukreti/munch.rs/contents/{+path}", "compare_url": "https://api.github.com/repos/utkarshkukreti/munch.rs/compare/{base}...{head}", "merges_url": "https://api.github.com/repos/utkarshkukreti/munch.rs/merges", "archive_url": "https://api.github.com/repos/utkarshkukreti/munch.rs/{archive_format}{/ref}", "downloads_url": "https://api.github.com/repos/utkarshkukreti/munch.rs/downloads", "issues_url": "https://api.github.com/repos/utkarshkukreti/munch.rs/issues{/number}", "pulls_url": "https://api.github.com/repos/utkarshkukreti/munch.rs/pulls{/number}", "milestones_url": "https://api.github.com/repos/utkarshkukreti/munch.rs/milestones{/number}", "notifications_url": "https://api.github.com/repos/utkarshkukreti/munch.rs/notifications{?since,all,participating}", "labels_url": "https://api.github.com/repos/utkarshkukreti/munch.rs/labels{/name}", "releases_url": "https://api.github.com/repos/utkarshkukreti/munch.rs/releases{/id}", "deployments_url": "https://api.github.com/repos/utkarshkukreti/munch.rs/deployments", "created_at": "2017-02-26T06:04:46Z", "updated_at": "2022-04-25T14:17:01Z", "pushed_at": "2021-08-09T15:17:45Z", "git_url": "git://github.com/utkarshkukreti/munch.rs.git", "ssh_url": "git@github.com:utkarshkukreti/munch.rs.git", "clone_url": "https://github.com/utkarshkukreti/munch.rs.git", "svn_url": "https://github.com/utkarshkukreti/munch.rs", "homepage": "", "size": 103, "stargazers_count": 21, "watchers_count": 21, "language": "Rust", "has_issues": true, "has_projects": true, "has_downloads": true, "has_wiki": true, "has_pages": false, "forks_count": 0, "mirror_url": null, "archived": false, "disabled": false, "open_issues_count": 0, "license": null, "allow_forking": true, "is_template": false, "topics": [], "visibility": "public", "forks": 0, "open_issues": 0, "watchers": 21, "default_branch": "master", "permissions": {"admin": false, "maintain": false, "push": false, "triage": false, "pull": true}, "score": 1.0}, {"id": 110645517, "node_id": "MDEwOlJlcG9zaXRvcnkxMTA2NDU1MTc=", "name": "Rust", "full_name": "MozMPCG/Rust", "private": false, "owner": {"login": "MozMPCG", "id": 31701922, "node_id": "MDEyOk9yZ2FuaXphdGlvbjMxNzAxOTIy", "avatar_url": "https://avatars.githubusercontent.com/u/31701922?v=4", "gravatar_id": "", "url": "https://api.github.com/users/MozMPCG", "html_url": "https://github.com/MozMPCG", "followers_url": "https://api.github.com/users/MozMPCG/followers", "following_url": "https://api.github.com/users/MozMPCG/following{/other_user}", "gists_url": "https://api.github.com/users/MozMPCG/gists{/gist_id}", "starred_url": "https://api.github.com/users/MozMPCG/starred{/owner}{/repo}", "subscriptions_url": "https://api.github.com/users/MozMPCG/subscriptions", "organizations_url": "https://api.github.com/users/MozMPCG/orgs", "repos_url": "https://api.github.com/users/MozMPCG/repos", "events_url": "https://api.github.com/users/MozMPCG/events{/privacy}", "received_events_url": "https://api.github.com/users/MozMPCG/received_events", "type": "Organization", "site_admin": false}, "html_url": "https://github.com/MozMPCG/Rust", "description": "A systems programming language that runs blazingly fast, prevents segfaults, and guarantees thread safety.", "fork": false, "url": "https://api.github.com/repos/MozMPCG/Rust", "forks_url": "https://api.github.com/repos/MozMPCG/Rust/forks", "keys_url": "https://api.github.com/repos/MozMPCG/Rust/keys{/key_id}", "collaborators_url": "https://api.github.com/repos/MozMPCG/Rust/collaborators{/collaborator}", "teams_url": "https://api.github.com/repos/MozMPCG/Rust/teams", "hooks_url": "https://api.github.com/repos/MozMPCG/Rust/hooks", "issue_events_url": "https://api.github.com/repos/MozMPCG/Rust/issues/events{/number}", "events_url": "https://api.github.com/repos/MozMPCG/Rust/events", "assignees_url": "https://api.github.com/repos/MozMPCG/Rust/assignees{/user}", "branches_url": "https://api.github.com/repos/MozMPCG/Rust/branches{/branch}", "tags_url": "https://api.github.com/repos/MozMPCG/Rust/tags", "blobs_url": "https://api.github.com/repos/MozMPCG/Rust/git/blobs{/sha}", "git_tags_url": "https://api.github.com/repos/MozMPCG/Rust/git/tags{/sha}", "git_refs_url": "https://api.github.com/repos/MozMPCG/Rust/git/refs{/sha}", "trees_url": "https://api.github.com/repos/MozMPCG/Rust/git/trees{/sha}", "statuses_url": "https://api.github.com/repos/MozMPCG/Rust/statuses/{sha}", "languages_url": "https://api.github.com/repos/MozMPCG/Rust/languages", "stargazers_url": "https://api.github.com/repos/MozMPCG/Rust/stargazers", "contributors_url": "https://api.github.com/repos/MozMPCG/Rust/contributors", "subscribers_url": "https://api.github.com/repos/MozMPCG/Rust/subscribers", "subscription_url": "https://api.github.com/repos/MozMPCG/Rust/subscription", "commits_url": "https://api.github.com/repos/MozMPCG/Rust/commits{/sha}", "git_commits_url": "https://api.github.com/repos/MozMPCG/Rust/git/commits{/sha}", "comments_url": "https://api.github.com/repos/MozMPCG/Rust/comments{/number}", "issue_comment_url": "https://api.github.com/repos/MozMPCG/Rust/issues/comments{/number}", "contents_url": "https://api.github.com/repos/MozMPCG/Rust/contents/{+path}", "compare_url": "https://api.github.com/repos/MozMPCG/Rust/compare/{base}...{head}", "merges_url": "https://api.github.com/repos/MozMPCG/Rust/merges", "archive_url": "https://api.github.com/repos/MozMPCG/Rust/{archive_format}{/ref}", "downloads_url": "https://api.github.com/repos/MozMPCG/Rust/downloads", "issues_url": "https://api.github.com/repos/MozMPCG/Rust/issues{/number}", "pulls_url": "https://api.github.com/repos/MozMPCG/Rust/pulls{/number}", "milestones_url": "https://api.github.com/repos/MozMPCG/Rust/milestones{/number}", "notifications_url": "https://api.github.com/repos/MozMPCG/Rust/notifications{?since,all,participating}", "labels_url": "https://api.github.com/repos/MozMPCG/Rust/labels{/name}", "releases_url": "https://api.github.com/repos/MozMPCG/Rust/releases{/id}", "deployments_url": "https://api.github.com/repos/MozMPCG/Rust/deployments", "created_at": "2017-11-14T05:37:49Z", "updated_at": "2017-11-14T05:48:29Z", "pushed_at": "2017-11-16T11:04:31Z", "git_url": "git://github.com/MozMPCG/Rust.git", "ssh_url": "git@github.com:MozMPCG/Rust.git", "clone_url": "https://github.com/MozMPCG/Rust.git", "svn_url": "https://github.com/MozMPCG/Rust", "homepage": null, "size": 24, "stargazers_count": 0, "watchers_count": 0, "language": "Rust", "has_issues": true, "has_projects": true, "has_downloads": true, "has_wiki": true, "has_pages": false, "forks_count": 1, "mirror_url": null, "archived": false, "disabled": false, "open_issues_count": 0, "license": {"key": "mpl-2.0", "name": "Mozilla Public License 2.0", "spdx_id": "MPL-2.0", "url": "https://api.github.com/licenses/mpl-2.0", "node_id": "MDc6TGljZW5zZTE0"}, "allow_forking": true, "is_template": false, "topics": [], "visibility": "public", "forks": 1, "open_issues": 0, "watchers": 0, "default_branch": "master", "permissions": {"admin": false, "maintain": false, "push": false, "triage": false, "pull": true}, "score": 1.0}]}