{"total_count": 3, "incomplete_results": false, "items": [{"id": 475090243, "node_id": "R_kgDOHFFNQw", "name": "feather", "full_name": "getfeatherapp/feather", "private": false, "owner": {"login": "getfeatherapp", "id": 102429357, "node_id": "U_kgDOBhryrQ", "avatar_url": "https://avatars.githubusercontent.com/u/102429357?v=4", "gravatar_id": "", "url": "https://api.github.com/users/getfeatherapp", "html_url": "https://github.com/getfeatherapp", "followers_url": "https://api.github.com/users/getfeatherapp/followers", "following_url": "https://api.github.com/users/getfeatherapp/following{/other_user}", "gists_url": "https://api.github.com/users/getfeatherapp/gists{/gist_id}", "starred_url": "https://api.github.com/users/getfeatherapp/starred{/owner}{/repo}", "subscriptions_url": "https://api.github.com/users/getfeatherapp/subscriptions", "organizations_url": "https://api.github.com/users/getfeatherapp/orgs", "repos_url": "https://api.github.com/users/getfeatherapp/repos", "events_url": "https://api.github.com/users/getfeatherapp/events{/privacy}", "received_events_url": "https://api.github.com/users/getfeatherapp/received_events", "type": "User", "site_admin": false}, "html_url": "https://github.com/getfeatherapp/feather", "description": "A lightweight, blazingly fast flat-file website engine.", "fork": false, "url": "https://api.github.com/repos/getfeatherapp/feather", "forks_url": "https://api.github.com/repos/getfeatherapp/feather/forks", "keys_url": "https://api.github.com/repos/getfeatherapp/feather/keys{/key_id}", "collaborators_url": "https://api.github.com/repos/getfeatherapp/feather/collaborators{/collaborator}", "teams_url": "https://api.github.com/repos/getfeatherapp/feather/teams", "hooks_url": "https://api.github.com/repos/getfeatherapp/feather/hooks", "issue_events_url": "https://api.github.com/repos/getfeatherapp/feather/issues/events{/number}", "events_url": "https://api.github.com/repos/getfeatherapp/feather/events", "assignees_url": "https://api.github.com/repos/getfeatherapp/feather/assignees{/user}", "branches_url": "https://api.github.com/repos/getfeatherapp/feather/branches{/branch}", "tags_url": "https://api.github.com/repos/getfeatherapp/feather/tags", "blobs_url": "https://api.github.com/repos/getfeatherapp/feather/git/blobs{/sha}", "git_tags_url": "https://api.github.com/repos/getfeatherapp/feather/git/tags{/sha}", "git_refs_url": "https://api.github.com/repos/getfeatherapp/feather/git/refs{/sha}", "trees_url": "https://api.github.com/repos/getfeatherapp/feather/git/trees{/sha}", "statuses_url": "https://api.github.com/repos/getfeatherapp/feather/statuses/{sha}", "languages_url": "https://api.github.com/repos/getfeatherapp/feather/languages", "stargazers_url": "https://api.github.com/repos/getfeatherapp/feather/stargazers", "contributors_url": "https://api.github.com/repos/getfeatherapp/feather/contributors", "subscribers_url": "https://api.github.com/repos/getfeatherapp/feather/subscribers", "subscription_url": "https://api.github.com/repos/getfeatherapp/feather/subscription", "commits_url": "https://api.github.com/repos/getfeatherapp/feather/commits{/sha}", "git_commits_url": "https://api.github.com/repos/getfeatherapp/feather/git/commits{/sha}", "comments_url": "https://api.github.com/repos/getfeatherapp/feather/comments{/number}", "issue_comment_url": "https://api.github.com/repos/getfeatherapp/feather/issues/comments{/number}", "contents_url": "https://api.github.com/repos/getfeatherapp/feather/contents/{+path}", "compare_url": "https://api.github.com/repos/getfeatherapp/feather/compare/{base}...{head}", "merges_url": "https://api.github.com/repos/getfeatherapp/feather/merges", "archive_url": "https://api.github.com/repos/getfeatherapp/feather/{archive_format}{/ref}", "downloads_url": "https://api.github.com/repos/getfeatherapp/feather/downloads", "issues_url": "https://api.github.com/repos/getfeatherapp/feather/issues{/number}", "pulls_url": "https://api.github.com/repos/getfeatherapp/feather/pulls{/number}", "milestones_url": "https://api.github.com/repos/getfeatherapp/feather/milestones{/number}", "notifications_url": "https://api.github.com/repos/getfeatherapp/feather/notifications{?since,all,participating}", "labels_url": "https://api.github.com/repos/getfeatherapp/feather/labels{/name}", "releases_url": "https://api.github.com/repos/getfeatherapp/feather/releases{/id}", "deployments_url": "https://api.github.com/repos/getfeatherapp/feather/deployments", "created_at": "2022-03-28T16:38:04Z", "updated_at": "2022-04-10T07:42:32Z", "pushed_at": "2022-04-13T11:03:02Z", "git_url": "git://github.com/getfeatherapp/feather.git", "ssh_url": "git@github.com:getfeatherapp/feather.git", "clone_url": "https://github.com/getfeatherapp/feather.git", "svn_url": "https://github.com/getfeatherapp/feather", "homepage": null, "size": 265, "stargazers_count": 1, "watchers_count": 1, "language": "PHP", "has_issues": true, "has_projects": true, "has_downloads": true, "has_wiki": true, "has_pages": false, "forks_count": 2, "mirror_url": null, "archived": false, "disabled": false, "open_issues_count": 0, "license": {"key": "mit", "name": "MIT License", "spdx_id": "MIT", "url": "https://api.github.com/licenses/mit", "node_id": "MDc6TGljZW5zZTEz"}, "allow_forking": true, "is_template": false, "topics": [], "visibility": "public", "forks": 2, "open_issues": 0, "watchers": 1, "default_branch": "main", "permissions": {"admin": false, "maintain": false, "push": false, "triage": false, "pull": true}, "score": 1.0}, {"id": 458134943, "node_id": "R_kgDOG06Vnw", "name": "baristawp-plugin", "full_name": "fnpen/baristawp-plugin", "private": false, "owner": {"login": "fnpen", "id": 31767378, "node_id": "MDQ6VXNlcjMxNzY3Mzc4", "avatar_url": "https://avatars.githubusercontent.com/u/31767378?v=4", "gravatar_id": "", "url": "https://api.github.com/users/fnpen", "html_url": "https://github.com/fnpen", "followers_url": "https://api.github.com/users/fnpen/followers", "following_url": "https://api.github.com/users/fnpen/following{/other_user}", "gists_url": "https://api.github.com/users/fnpen/gists{/gist_id}", "starred_url": "https://api.github.com/users/fnpen/starred{/owner}{/repo}", "subscriptions_url": "https://api.github.com/users/fnpen/subscriptions", "organizations_url": "https://api.github.com/users/fnpen/orgs", "repos_url": "https://api.github.com/users/fnpen/repos", "events_url": "https://api.github.com/users/fnpen/events{/privacy}", "received_events_url": "https://api.github.com/users/fnpen/received_events", "type": "User", "site_admin": false}, "html_url": "https://github.com/fnpen/baristawp-plugin", "description": "Barista is a blazingly fast, totally extendable command launcher. It lets you go your routine tasks faster, search posts, control your site, and much more.", "fork": false, "url": "https://api.github.com/repos/fnpen/baristawp-plugin", "forks_url": "https://api.github.com/repos/fnpen/baristawp-plugin/forks", "keys_url": "https://api.github.com/repos/fnpen/baristawp-plugin/keys{/key_id}", "collaborators_url": "https://api.github.com/repos/fnpen/baristawp-plugin/collaborators{/collaborator}", "teams_url": "https://api.github.com/repos/fnpen/baristawp-plugin/teams", "hooks_url": "https://api.github.com/repos/fnpen/baristawp-plugin/hooks", "issue_events_url": "https://api.github.com/repos/fnpen/baristawp-plugin/issues/events{/number}", "events_url": "https://api.github.com/repos/fnpen/baristawp-plugin/events", "assignees_url": "https://api.github.com/repos/fnpen/baristawp-plugin/assignees{/user}", "branches_url": "https://api.github.com/repos/fnpen/baristawp-plugin/branches{/branch}", "tags_url": "https://api.github.com/repos/fnpen/baristawp-plugin/tags", "blobs_url": "https://api.github.com/repos/fnpen/baristawp-plugin/git/blobs{/sha}", "git_tags_url": "https://api.github.com/repos/fnpen/baristawp-plugin/git/tags{/sha}", "git_refs_url": "https://api.github.com/repos/fnpen/baristawp-plugin/git/refs{/sha}", "trees_url": "https://api.github.com/repos/fnpen/baristawp-plugin/git/trees{/sha}", "statuses_url": "https://api.github.com/repos/fnpen/baristawp-plugin/statuses/{sha}", "languages_url": "https://api.github.com/repos/fnpen/baristawp-plugin/languages", "stargazers_url": "https://api.github.com/repos/fnpen/baristawp-plugin/stargazers", "contributors_url": "https://api.github.com/repos/fnpen/baristawp-plugin/contributors", "subscribers_url": "https://api.github.com/repos/fnpen/baristawp-plugin/subscribers", "subscription_url": "https://api.github.com/repos/fnpen/baristawp-plugin/subscription", "commits_url": "https://api.github.com/repos/fnpen/baristawp-plugin/commits{/sha}", "git_commits_url": "https://api.github.com/repos/fnpen/baristawp-plugin/git/commits{/sha}", "comments_url": "https://api.github.com/repos/fnpen/baristawp-plugin/comments{/number}", "issue_comment_url": "https://api.github.com/repos/fnpen/baristawp-plugin/issues/comments{/number}", "contents_url": "https://api.github.com/repos/fnpen/baristawp-plugin/contents/{+path}", "compare_url": "https://api.github.com/repos/fnpen/baristawp-plugin/compare/{base}...{head}", "merges_url": "https://api.github.com/repos/fnpen/baristawp-plugin/merges", "archive_url": "https://api.github.com/repos/fnpen/baristawp-plugin/{archive_format}{/ref}", "downloads_url": "https://api.github.com/repos/fnpen/baristawp-plugin/downloads", "issues_url": "https://api.github.com/repos/fnpen/baristawp-plugin/issues{/number}", "pulls_url": "https://api.github.com/repos/fnpen/baristawp-plugin/pulls{/number}", "milestones_url": "https://api.github.com/repos/fnpen/baristawp-plugin/milestones{/number}", "notifications_url": "https://api.github.com/repos/fnpen/baristawp-plugin/notifications{?since,all,participating}", "labels_url": "https://api.github.com/repos/fnpen/baristawp-plugin/labels{/name}", "releases_url": "https://api.github.com/repos/fnpen/baristawp-plugin/releases{/id}", "deployments_url": "https://api.github.com/repos/fnpen/baristawp-plugin/deployments", "created_at": "2022-02-11T10:09:19Z", "updated_at": "2022-02-18T12:11:15Z", "pushed_at": "2022-02-23T09:05:04Z", "git_url": "git://github.com/fnpen/baristawp-plugin.git", "ssh_url": "git@github.com:fnpen/baristawp-plugin.git", "clone_url": "https://github.com/fnpen/baristawp-plugin.git", "svn_url": "https://github.com/fnpen/baristawp-plugin", "homepage": "", "size": 646, "stargazers_count": 5, "watchers_count": 5, "language": "PHP", "has_issues": true, "has_projects": true, "has_downloads": true, "has_wiki": true, "has_pages": false, "forks_count": 0, "mirror_url": null, "archived": false, "disabled": false, "open_issues_count": 1, "license": null, "allow_forking": true, "is_template": false, "topics": ["woocommerce", "woocommerce-plugin", "wordpress", "wordpress-development", "wordpress-plugin"], "visibility": "public", "forks": 0, "open_issues": 1, "watchers": 5, "default_branch": "main", "permissions": {"admin": false, "maintain": false, "push": false, "triage": false, "pull": true}, "score": 1.0}, {"id": 455503018, "node_id": "R_kgDOGyZsqg", "name": "mediawiki-template-parser", "full_name": "WikibaseSolutions/mediawiki-template-parser", "private": false, "owner": {"login": "WikibaseSolutions", "id": 22588228, "node_id": "MDEyOk9yZ2FuaXphdGlvbjIyNTg4MjI4", "avatar_url": "https://avatars.githubusercontent.com/u/22588228?v=4", "gravatar_id": "", "url": "https://api.github.com/users/WikibaseSolutions", "html_url": "https://github.com/WikibaseSolutions", "followers_url": "https://api.github.com/users/WikibaseSolutions/followers", "following_url": "https://api.github.com/users/WikibaseSolutions/following{/other_user}", "gists_url": "https://api.github.com/users/WikibaseSolutions/gists{/gist_id}", "starred_url": "https://api.github.com/users/WikibaseSolutions/starred{/owner}{/repo}", "subscriptions_url": "https://api.github.com/users/WikibaseSolutions/subscriptions", "organizations_url": "https://api.github.com/users/WikibaseSolutions/orgs", "repos_url": "https://api.github.com/users/WikibaseSolutions/repos", "events_url": "https://api.github.com/users/WikibaseSolutions/events{/privacy}", "received_events_url": "https://api.github.com/users/WikibaseSolutions/received_events", "type": "Organization", "site_admin": false}, "html_url": "https://github.com/WikibaseSolutions/mediawiki-template-parser", "description": "A blazing fast template parser for MediaWiki.", "fork": false, "url": "https://api.github.com/repos/WikibaseSolutions/mediawiki-template-parser", "forks_url": "https://api.github.com/repos/WikibaseSolutions/mediawiki-template-parser/forks", "keys_url": "https://api.github.com/repos/WikibaseSolutions/mediawiki-template-parser/keys{/key_id}", "collaborators_url": "https://api.github.com/repos/WikibaseSolutions/mediawiki-template-parser/collaborators{/collaborator}", "teams_url": "https://api.github.com/repos/WikibaseSolutions/mediawiki-template-parser/teams", "hooks_url": "https://api.github.com/repos/WikibaseSolutions/mediawiki-template-parser/hooks", "issue_events_url": "https://api.github.com/repos/WikibaseSolutions/mediawiki-template-parser/issues/events{/number}", "events_url": "https://api.github.com/repos/WikibaseSolutions/mediawiki-template-parser/events", "assignees_url": "https://api.github.com/repos/WikibaseSolutions/mediawiki-template-parser/assignees{/user}", "branches_url": "https://api.github.com/repos/WikibaseSolutions/mediawiki-template-parser/branches{/branch}", "tags_url": "https://api.github.com/repos/WikibaseSolutions/mediawiki-template-parser/tags", "blobs_url": "https://api.github.com/repos/WikibaseSolutions/mediawiki-template-parser/git/blobs{/sha}", "git_tags_url": "https://api.github.com/repos/WikibaseSolutions/mediawiki-template-parser/git/tags{/sha}", "git_refs_url": "https://api.github.com/repos/WikibaseSolutions/mediawiki-template-parser/git/refs{/sha}", "trees_url": "https://api.github.com/repos/WikibaseSolutions/mediawiki-template-parser/git/trees{/sha}", "statuses_url": "https://api.github.com/repos/WikibaseSolutions/mediawiki-template-parser/statuses/{sha}", "languages_url": "https://api.github.com/repos/WikibaseSolutions/mediawiki-template-parser/languages", "stargazers_url": "https://api.github.com/repos/WikibaseSolutions/mediawiki-template-parser/stargazers", "contributors_url": "https://api.github.com/repos/WikibaseSolutions/mediawiki-template-parser/contributors", "subscribers_url": "https://api.github.com/repos/WikibaseSolutions/mediawiki-template-parser/subscribers", "subscription_url": "https://api.github.com/repos/WikibaseSolutions/mediawiki-template-parser/subscription", "commits_url": "https://api.github.com/repos/WikibaseSolutions/mediawiki-template-parser/commits{/sha}", "git_commits_url": "https://api.github.com/repos/WikibaseSolutions/mediawiki-template-parser/git/commits{/sha}", "comments_url": "https://api.github.com/repos/WikibaseSolutions/mediawiki-template-parser/comments{/number}", "issue_comment_url": "https://api.github.com/repos/WikibaseSolutions/mediawiki-template-parser/issues/comments{/number}", "contents_url": "https://api.github.com/repos/WikibaseSolutions/mediawiki-template-parser/contents/{+path}", "compare_url": "https://api.github.com/repos/WikibaseSolutions/mediawiki-template-parser/compare/{base}...{head}", "merges_url": "https://api.github.com/repos/WikibaseSolutions/mediawiki-template-parser/merges", "archive_url": "https://api.github.com/repos/WikibaseSolutions/mediawiki-template-parser/{archive_format}{/ref}", "downloads_url": "https://api.github.com/repos/WikibaseSolutions/mediawiki-template-parser/downloads", "issues_url": "https://api.github.com/repos/WikibaseSolutions/mediawiki-template-parser/issues{/number}", "pulls_url": "https://api.github.com/repos/WikibaseSolutions/mediawiki-template-parser/pulls{/number}", "milestones_url": "https://api.github.com/repos/WikibaseSolutions/mediawiki-template-parser/milestones{/number}", "notifications_url": "https://api.github.com/repos/WikibaseSolutions/mediawiki-template-parser/notifications{?since,all,participating}", "labels_url": "https://api.github.com/repos/WikibaseSolutions/mediawiki-template-parser/labels{/name}", "releases_url": "https://api.github.com/repos/WikibaseSolutions/mediawiki-template-parser/releases{/id}", "deployments_url": "https://api.github.com/repos/WikibaseSolutions/mediawiki-template-parser/deployments", "created_at": "2022-02-04T10:19:31Z", "updated_at": "2022-02-04T10:21:13Z", "pushed_at": "2022-05-10T07:11:02Z", "git_url": "git://github.com/WikibaseSolutions/mediawiki-template-parser.git", "ssh_url": "git@github.com:WikibaseSolutions/mediawiki-template-parser.git", "clone_url": "https://github.com/WikibaseSolutions/mediawiki-template-parser.git", "svn_url": "https://github.com/WikibaseSolutions/mediawiki-template-parser", "homepage": null, "size": 37, "stargazers_count": 0, "watchers_count": 0, "language": "PHP", "has_issues": true, "has_projects": true, "has_downloads": true, "has_wiki": true, "has_pages": false, "forks_count": 0, "mirror_url": null, "archived": false, "disabled": false, "open_issues_count": 0, "license": {"key": "gpl-3.0", "name": "GNU General Public License v3.0", "spdx_id": "GPL-3.0", "url": "https://api.github.com/licenses/gpl-3.0", "node_id": "MDc6TGljZW5zZTk="}, "allow_forking": true, "is_template": false, "topics": [], "visibility": "public", "forks": 0, "open_issues": 0, "watchers": 0, "default_branch": "master", "permissions": {"admin": false, "maintain": false, "push": false, "triage": false, "pull": true}, "score": 1.0}]}